{"initDir":"/home/runner/work/owlkettle/owlkettle","cfgDir":"/home/runner/work/owlkettle/owlkettle","rawCfg":"[nimib]\nsrcDir = \".\"\nhomeDir = \"compiledBook\"\n\n[nimibook]\nlanguage = \"en-us\"\ntitle = \"Owlkettle\"\ndescription = \"Freshly brewed user interfaces.\"\ngit_repository_url = \"https://github.com/can-lehmann/owlkettle\"\ndefault_theme = \"Rust\"","nbCfg":{"srcDir":".","homeDir":"compiledBook"},"cfg":{"title":"Owlkettle","language":"en-us","description":"Freshly brewed user interfaces.","default_theme":"Rust","preferred_dark_theme":"navy","git_repository_url":"https://github.com/can-lehmann/owlkettle","git_repository_icon":"fa-github","plausible_analytics_url":"","favicon_escaped":"<link rel=\"icon\" href=\"data:image/svg+xml,<svg xmlns=%22http://www.w3.org/2000/svg%22 viewBox=%220 0 100 100%22><text y=%22.9em%22 font-size=%2280%22>🐳</text></svg>\">"},"theme_option":{"navy":"Navy","coal":"Coal","rust":"Rust","ayu":"Ayu","light":"Light (default)"},"toc":{"entries":[{"title":"Welcome to Owlkettle!","path":"README.md","levels":[1],"isNumbered":true,"isDraft":false,"isActive":false},{"title":"Tutorial","path":"docs/tutorial.md","levels":[2],"isNumbered":true,"isDraft":false,"isActive":false},{"title":"General Examples","path":"examples/README.md","levels":[3],"isNumbered":true,"isDraft":false,"isActive":false},{"title":"Tooling","path":"docs/recommended_tools.md","levels":[4],"isNumbered":true,"isDraft":false,"isActive":false},{"title":"Reference","path":"book/reference.nim","levels":[5],"isNumbered":true,"isDraft":false,"isActive":false},{"title":"General Widget Reference","path":"docs/widgets.md","levels":[5,1],"isNumbered":true,"isDraft":false,"isActive":false},{"title":"Adwaita Widget Reference","path":"docs/widgets_adwaita.md","levels":[5,2],"isNumbered":true,"isDraft":false,"isActive":false},{"title":"DataEntry Widget Reference","path":"docs/widgets_dataentries.md","levels":[5,3],"isNumbered":true,"isDraft":false,"isActive":false},{"title":"Internals","path":"book/internals.nim","levels":[6],"isNumbered":true,"isDraft":false,"isActive":false},{"title":"Custom Widgets","path":"book/internals/custom_widgets.nim","levels":[6,1],"isNumbered":true,"isDraft":false,"isActive":false},{"title":"Adders","path":"book/internals/adders.nim","levels":[6,2],"isNumbered":true,"isDraft":false,"isActive":false},{"title":"One Adder","path":"book/internals/adders/one_adder.nim","levels":[6,2,1],"isNumbered":true,"isDraft":false,"isActive":false},{"title":"Adders With Properties","path":"book/internals/adders/adders_with_properties.nim","levels":[6,2,2],"isNumbered":true,"isDraft":false,"isActive":false},{"title":"Multiple Adders","path":"book/internals/adders/multiple_adders.nim","levels":[6,2,3],"isNumbered":true,"isDraft":false,"isActive":false},{"title":"Hooks","path":"book/internals/hooks.nim","levels":[6,3],"isNumbered":true,"isDraft":false,"isActive":false},{"title":"Build Hook","path":"book/internals/hooks/build_hook.nim","levels":[6,3,1],"isNumbered":true,"isDraft":false,"isActive":false},{"title":"BeforeBuild Hook","path":"book/internals/hooks/before_build_hook.nim","levels":[6,3,2],"isNumbered":true,"isDraft":false,"isActive":false},{"title":"AfterBuild Hook","path":"book/internals/hooks/after_build_hook.nim","levels":[6,3,3],"isNumbered":true,"isDraft":false,"isActive":false},{"title":"Event Hooks","path":"book/internals/hooks/event_hooks.nim","levels":[6,3,4],"isNumbered":true,"isDraft":false,"isActive":false},{"title":"Update Hook","path":"book/internals/hooks/update_hook.nim","levels":[6,3,5],"isNumbered":true,"isDraft":false,"isActive":false},{"title":"Property Hook","path":"book/internals/hooks/property_hook.nim","levels":[6,3,6],"isNumbered":true,"isDraft":false,"isActive":false},{"title":"Read Hook","path":"book/internals/hooks/read_hook.nim","levels":[6,3,7],"isNumbered":true,"isDraft":false,"isActive":false},{"title":"Contributing","path":"CONTRIBUTING.md","levels":[7],"isNumbered":true,"isDraft":false,"isActive":false}]},"keep":[]}